json4e/__init__.py
json4e/base.py
json4e-1.0.0.dist-info/METADATA
json4e-1.0.0.dist-info/RECORD
json4e-1.0.0.dist-info/WHEEL
json4e-1.0.0.dist-info/top_level.txt
